[
  {
    "ID": 3999.0,
    "Name": "Player",
    "Kind": 0.0,
    "Gender": "Male",
    "HP": 600.0,
    "Sight": 30.0,
    "Speed": 5.0,
    "SummonOrder": 0.0,
    "FocusIconName": "CharacterFocusIcon_Player",
    "PrefabPath": null,
    "UIPrefabPath": "NULL",
    "UIHUDStateHeight": 4.5
  },
  {
    "ID": 3000.0,
    "Name": "SR_Minion",
    "Kind": 1.0,
    "Gender": "Genderlessness",
    "HP": 200.0,
    "Sight": 20.0,
    "Speed": 3.0,
    "SummonOrder": 1.0,
    "FocusIconName": "CharacterFocusIcon_SR_Minion",
    "PrefabPath": "Assets/AddressableResources/Prefabs/Objects/Character/Daisy.prefab",
    "UIPrefabPath": "Assets/AddressableResources/Prefabs/Objects/UICharacter/UI_Daisy.prefab",
    "UIHUDStateHeight": 3.0
  },
  {
    "ID": 3001.0,
    "Name": "LR_Minion",
    "Kind": 1.0,
    "Gender": "Genderlessness",
    "HP": 150.0,
    "Sight": 30.0,
    "Speed": 3.0,
    "SummonOrder": 1.0,
    "FocusIconName": "CharacterFocusIcon_LR_Minion",
    "PrefabPath": "Assets/AddressableResources/Prefabs/Objects/Character/Anne.prefab",
    "UIPrefabPath": "Assets/AddressableResources/Prefabs/Objects/UICharacter/UI_Anne.prefab",
    "UIHUDStateHeight": 3.0
  },
  {
    "ID": 3002.0,
    "Name": "CN_Minion",
    "Kind": 1.0,
    "Gender": "Genderlessness",
    "HP": 350.0,
    "Sight": 30.0,
    "Speed": 3.0,
    "SummonOrder": 1.0,
    "FocusIconName": "CharacterFocusIcon_CN_Minion",
    "PrefabPath": "Assets/AddressableResources/Prefabs/Objects/Character/Anne.prefab",
    "UIPrefabPath": "Assets/AddressableResources/Prefabs/Objects/UICharacter/UI_Anne.prefab",
    "UIHUDStateHeight": 4.0
  },
  {
    "ID": 3003.0,
    "Name": "Baron",
    "Kind": 1.0,
    "Gender": "Genderlessness",
    "HP": 3000.0,
    "Sight": 30.0,
    "Speed": 0.0,
    "SummonOrder": 1.0,
    "FocusIconName": "CharacterFocusIcon_CN_Baron",
    "PrefabPath": "Assets/AddressableResources/Prefabs/Objects/Character/Anne.prefab",
    "UIPrefabPath": "Assets/AddressableResources/Prefabs/Objects/UICharacter/UI_Anne.prefab",
    "UIHUDStateHeight": 7.0
  },
  {
    "ID": 3004.0,
    "Name": "Dragon",
    "Kind": 1.0,
    "Gender": "Genderlessness",
    "HP": 2000.0,
    "Sight": 30.0,
    "Speed": 0.0,
    "SummonOrder": 1.0,
    "FocusIconName": "CharacterFocusIcon_CN_Baron",
    "PrefabPath": "Assets/AddressableResources/Prefabs/Objects/Character/Anne.prefab",
    "UIPrefabPath": "Assets/AddressableResources/Prefabs/Objects/UICharacter/UI_Anne.prefab",
    "UIHUDStateHeight": 7.0
  }
]